cypcap/__init__.py
cypcap/_cypcap.cp38-win32.pyd
cypcap/bpf.cp38-win32.pyd
cypcap-0.6.2.dist-info/LICENSE
cypcap-0.6.2.dist-info/METADATA
cypcap-0.6.2.dist-info/NOTICE
cypcap-0.6.2.dist-info/WHEEL
cypcap-0.6.2.dist-info/top_level.txt
cypcap-0.6.2.dist-info/RECORD
