Metadata-Version: 2.1
Name: cypcap
Version: 0.6.2
Summary: A Cython based binding for modern libpcap
Home-page: https://github.com/segevfiner/cypcap
Author: Segev Finer
Author-email: segev208@gmail.com
License: BSD-3-Clause
Project-URL: Documentation, https://segevfiner.github.io/cypcap/
Project-URL: Issue Tracker, https://github.com/segevfiner/cypcap/issues
Keywords: libpcap pcap
Classifier: Development Status :: 4 - Beta
Classifier: Intended Audience :: Developers
Classifier: Topic :: System :: Networking :: Monitoring
Classifier: Programming Language :: Cython
Classifier: Programming Language :: Python :: 3
Classifier: Programming Language :: Python :: 3.6
Classifier: Programming Language :: Python :: 3.7
Classifier: Programming Language :: Python :: 3.8
Classifier: Programming Language :: Python :: 3.9
Classifier: Programming Language :: Python :: 3.10
Classifier: Programming Language :: Python :: 3.11
Classifier: Programming Language :: Python :: 3.12
Classifier: Programming Language :: Python :: 3.13
Requires-Python: >=3.6
License-File: LICENSE
License-File: NOTICE
Provides-Extra: dev
Requires-Dist: cython >=3.0.0 ; extra == 'dev'
Requires-Dist: sphinx ==7.* ; extra == 'dev'
Requires-Dist: pytest ; extra == 'dev'
Requires-Dist: dpkt ; extra == 'dev'
Requires-Dist: netifaces ; extra == 'dev'
